mkcd/__init__.py
mkcd/wrappers.py
mkcd/_bin/windows_x86_64/ADVAPI32.dll
mkcd/_bin/windows_x86_64/CRYPT32.dll
mkcd/_bin/windows_x86_64/GDI32.dll
mkcd/_bin/windows_x86_64/KERNEL32.DLL
mkcd/_bin/windows_x86_64/KERNELBASE.dll
mkcd/_bin/windows_x86_64/RPCRT4.dll
mkcd/_bin/windows_x86_64/USER32.dll
mkcd/_bin/windows_x86_64/awk.exe
mkcd/_bin/windows_x86_64/base32.exe
mkcd/_bin/windows_x86_64/base64.exe
mkcd/_bin/windows_x86_64/bcrypt.dll
mkcd/_bin/windows_x86_64/bunzip.exe
mkcd/_bin/windows_x86_64/bunzip2.exe
mkcd/_bin/windows_x86_64/bzcat.exe
mkcd/_bin/windows_x86_64/bzip.exe
mkcd/_bin/windows_x86_64/bzip2.exe
mkcd/_bin/windows_x86_64/cal.exe
mkcd/_bin/windows_x86_64/cat.exe
mkcd/_bin/windows_x86_64/chmod.exe
mkcd/_bin/windows_x86_64/chown.exe
mkcd/_bin/windows_x86_64/cksum.exe
mkcd/_bin/windows_x86_64/column.exe
mkcd/_bin/windows_x86_64/comm.exe
mkcd/_bin/windows_x86_64/compress.exe
mkcd/_bin/windows_x86_64/cp.exe
mkcd/_bin/windows_x86_64/csplit.exe
mkcd/_bin/windows_x86_64/curl.exe
mkcd/_bin/windows_x86_64/cut.exe
mkcd/_bin/windows_x86_64/date.exe
mkcd/_bin/windows_x86_64/df.exe
mkcd/_bin/windows_x86_64/du.exe
mkcd/_bin/windows_x86_64/env.exe
mkcd/_bin/windows_x86_64/expand.exe
mkcd/_bin/windows_x86_64/expr.exe
mkcd/_bin/windows_x86_64/factor.exe
mkcd/_bin/windows_x86_64/false.exe
mkcd/_bin/windows_x86_64/file.exe
mkcd/_bin/windows_x86_64/find.exe
mkcd/_bin/windows_x86_64/fmt.exe
mkcd/_bin/windows_x86_64/fold.exe
mkcd/_bin/windows_x86_64/ftp.exe
mkcd/_bin/windows_x86_64/gawk.exe
mkcd/_bin/windows_x86_64/gdi32full.dll
mkcd/_bin/windows_x86_64/grep.exe
mkcd/_bin/windows_x86_64/groups.exe
mkcd/_bin/windows_x86_64/gzip.exe
mkcd/_bin/windows_x86_64/head.exe
mkcd/_bin/windows_x86_64/hexdump.exe
mkcd/_bin/windows_x86_64/hostname.exe
mkcd/_bin/windows_x86_64/id.exe
mkcd/_bin/windows_x86_64/install.exe
mkcd/_bin/windows_x86_64/join.exe
mkcd/_bin/windows_x86_64/kill.exe
mkcd/_bin/windows_x86_64/less.exe
mkcd/_bin/windows_x86_64/ln.exe
mkcd/_bin/windows_x86_64/locate.exe
mkcd-1.0.7.dist-info/licenses/LICENSE
mkcd-1.0.7.dist-info/METADATA
mkcd-1.0.7.dist-info/WHEEL
mkcd-1.0.7.dist-info/entry_points.txt
mkcd-1.0.7.dist-info/top_level.txt
mkcd-1.0.7.dist-info/RECORD
