Metadata-Version: 2.4
Name: mkcd
Version: 1.0.7
Summary: Get Linux utilities like tail,head,cat,cd,ls,cp,mv,rm in Windows directly without needing to manage WSL
Author-email: Tanjim Kamal <tanjimkamal1@gmail.com>
License-Expression: MIT
Project-URL: Homepage, https://github.com/itzmetanjim/mkcd
Project-URL: Issues, https://github.com/itzmetanjim/mkcd/issues
Classifier: Programming Language :: Python :: 3
Classifier: Operating System :: Microsoft :: Windows
Classifier: Environment :: Win32 (MS Windows)
Classifier: Topic :: Terminals
Classifier: Development Status :: 5 - Production/Stable
Requires-Python: >=3.9
License-File: LICENSE
Dynamic: license-file
